{"stats":{"minecraft:mined":{"minecraft:tall_grass":2,"minecraft:grass":4,"minecraft:sunflower":1},"minecraft:custom":{"minecraft:jump":316,"minecraft:open_chest":1,"minecraft:time_since_rest":9008,"minecraft:play_one_minute":9008,"minecraft:leave_game":1,"minecraft:sprint_one_cm":43767,"minecraft:damage_taken":20,"minecraft:time_since_death":9008,"minecraft:walk_one_cm":15240,"minecraft:interact_with_cartography_table":1,"minecraft:fall_one_cm":1298,"minecraft:fly_one_cm":169827}},"DataVersion":2586}